pertchart/__init__.py
pertchart/pertchart.py
pertchart-0.5.1.dist-info/LICENSE
pertchart-0.5.1.dist-info/METADATA
pertchart-0.5.1.dist-info/WHEEL
pertchart-0.5.1.dist-info/top_level.txt
pertchart-0.5.1.dist-info/RECORD
