Metadata-Version: 2.1
Name: pertchart
Version: 0.5.1
Summary: PERT chart generator
Home-page: https://github.com/sisayie/pertchart
Author: Sisay Chala
Author-email: sisayie@gmail.com
License: MIT
Keywords: pert chart,project plan,gantt
Platform: UNKNOWN
Classifier: Development Status :: 3 - Alpha
Classifier: Intended Audience :: Developers
Classifier: Topic :: Software Development :: Build Tools
Classifier: License :: OSI Approved :: MIT License
Classifier: Programming Language :: Python :: 3
Classifier: Programming Language :: Python :: 3.4
Classifier: Programming Language :: Python :: 3.5
Classifier: Programming Language :: Python :: 3.6
Classifier: Programming Language :: Python :: 3.7
Requires-Dist: graphviz
